timestampy/__init__.py
timestampy/cli.py
timestampy/timestampy.py
timestampy-0.1.2.dist-info/METADATA
timestampy-0.1.2.dist-info/RECORD
timestampy-0.1.2.dist-info/WHEEL
timestampy-0.1.2.dist-info/entry_points.txt
timestampy-0.1.2.dist-info/top_level.txt
