Metadata-Version: 2.1
Name: timestampy
Version: 0.1.2
Summary: Automatic timestamp generation on the blockchain.
Home-page: https://github.com/reale/timestampy
Author: Roberto Reale
Author-email: rober.reale@gmail.com
License: MIT license
Keywords: timestampy
Platform: UNKNOWN
Classifier: Development Status :: 2 - Pre-Alpha
Classifier: Intended Audience :: Developers
Classifier: License :: OSI Approved :: MIT License
Classifier: Natural Language :: English
Classifier: Programming Language :: Python :: 2
Classifier: Programming Language :: Python :: 2.7
Classifier: Programming Language :: Python :: 3
Classifier: Programming Language :: Python :: 3.4
Classifier: Programming Language :: Python :: 3.5
Classifier: Programming Language :: Python :: 3.6
Classifier: Programming Language :: Python :: 3.7
Requires-Dist: Click (>=6.0)
Requires-Dist: inotify
Requires-Dist: opentimestamps-client
